datapunt_api/__init__.py
datapunt_api/bbox.py
datapunt_api/pagination.py
datapunt_api/py.typed
datapunt_api/renderers.py
datapunt_api/rest.py
datapunt_api/serializers.py
datapunt_api/static/.release-it.json
datapunt_api/static/datapunt_api/bootstrap.min.css
datapunt_api/static/datapunt_api/datapunt.css
datapunt_api/static/fonts/glyphicons-halflings-regular.woff2
datapunt_api/templates/atlas_api/pagination.html
datapunt_api/templates/rest_framework/api.html
datapunt_api/templates/rest_framework/login.html
drf_amsterdam-1.1.0.dist-info/licenses/LICENSE
tests/__init__.py
tests/base_urls.py
tests/models.py
tests/serializers.py
tests/test_bbox.py
tests/test_pagination.py
tests/test_serializers.py
tests/test_settings.py
tests/urls.py
tests/views.py
drf_amsterdam-1.1.0.dist-info/METADATA
drf_amsterdam-1.1.0.dist-info/WHEEL
drf_amsterdam-1.1.0.dist-info/top_level.txt
drf_amsterdam-1.1.0.dist-info/RECORD
