Metadata-Version: 2.4
Name: drf_amsterdam
Version: 1.1.0
Summary: Amsterdam Datapunt code and style for Django REST Framework.
Author: Amsterdam Datapunt
Author-email: datapunt@amsterdam.nl
License: Mozilla Public License Version 2.0
Classifier: Development Status :: 5 - Production/Stable
Classifier: Intended Audience :: Developers
Classifier: Natural Language :: English
Classifier: Programming Language :: Python
Classifier: Programming Language :: Python :: 3.11
Classifier: License :: OSI Approved :: Mozilla Public License 2.0 (MPL 2.0)
License-File: LICENSE
Requires-Dist: djangorestframework
Requires-Dist: drf_extensions
Requires-Dist: djangorestframework_csv
Requires-Dist: djangorestframework_xml
Dynamic: author
Dynamic: author-email
Dynamic: classifier
Dynamic: description
Dynamic: description-content-type
Dynamic: license
Dynamic: license-file
Dynamic: requires-dist
Dynamic: summary
